IbmDeveloperworksQuanbuJiaochengYiFix1/README.md
IbmDeveloperworksQuanbuJiaochengYiFix1/__init__.py
IbmDeveloperworksQuanbuJiaochengYiFix1/__main__.py
IbmDeveloperworksQuanbuJiaochengYiFix1/file.epub
IbmDeveloperworksQuanbuJiaochengYiFix1/index.html
IbmDeveloperworksQuanbuJiaochengYiFix1/css/__init__.py
IbmDeveloperworksQuanbuJiaochengYiFix1/css/annotations.css
IbmDeveloperworksQuanbuJiaochengYiFix1/css/main.css
IbmDeveloperworksQuanbuJiaochengYiFix1/css/normalize.css
IbmDeveloperworksQuanbuJiaochengYiFix1/css/popup.css
IbmDeveloperworksQuanbuJiaochengYiFix1/font/__init__.py
IbmDeveloperworksQuanbuJiaochengYiFix1/font/fontello.eot
IbmDeveloperworksQuanbuJiaochengYiFix1/font/fontello.svg
IbmDeveloperworksQuanbuJiaochengYiFix1/font/fontello.ttf
IbmDeveloperworksQuanbuJiaochengYiFix1/font/fontello.woff
IbmDeveloperworksQuanbuJiaochengYiFix1/img/__init__.py
IbmDeveloperworksQuanbuJiaochengYiFix1/img/annotator-glyph-sprite.png
IbmDeveloperworksQuanbuJiaochengYiFix1/img/annotator-icon-sprite.png
IbmDeveloperworksQuanbuJiaochengYiFix1/img/apple-touch-icon.png
IbmDeveloperworksQuanbuJiaochengYiFix1/img/cancelfullscreen.png
IbmDeveloperworksQuanbuJiaochengYiFix1/img/close.png
IbmDeveloperworksQuanbuJiaochengYiFix1/img/fullscreen.png
IbmDeveloperworksQuanbuJiaochengYiFix1/img/loader.gif
IbmDeveloperworksQuanbuJiaochengYiFix1/img/menu-icon.png
IbmDeveloperworksQuanbuJiaochengYiFix1/img/save.png
IbmDeveloperworksQuanbuJiaochengYiFix1/img/saved.png
IbmDeveloperworksQuanbuJiaochengYiFix1/img/settings-s.png
IbmDeveloperworksQuanbuJiaochengYiFix1/img/settings.png
IbmDeveloperworksQuanbuJiaochengYiFix1/img/star.png
IbmDeveloperworksQuanbuJiaochengYiFix1/js/__init__.py
IbmDeveloperworksQuanbuJiaochengYiFix1/js/epub.js
IbmDeveloperworksQuanbuJiaochengYiFix1/js/epub.min.js
IbmDeveloperworksQuanbuJiaochengYiFix1/js/epub.min.map
IbmDeveloperworksQuanbuJiaochengYiFix1/js/hooks.min.js
IbmDeveloperworksQuanbuJiaochengYiFix1/js/hooks.min.map
ibm_developerworks_quanbu_jiaocheng_yi_fix1-2025.3.25.1.dist-info/METADATA
ibm_developerworks_quanbu_jiaocheng_yi_fix1-2025.3.25.1.dist-info/WHEEL
ibm_developerworks_quanbu_jiaocheng_yi_fix1-2025.3.25.1.dist-info/entry_points.txt
ibm_developerworks_quanbu_jiaocheng_yi_fix1-2025.3.25.1.dist-info/top_level.txt
ibm_developerworks_quanbu_jiaocheng_yi_fix1-2025.3.25.1.dist-info/RECORD
